biondi/__init__.py
biondi/dataset.py
biondi/models.py
biondi/random delete 2.py
biondi/random delete.py
biondi/random stuff.py
biondi/retinanet stuff.py
biondi/statistics.py
biondi/misc/DCGAN.py
biondi/misc/WSI autoencoder.py
biondi/misc/__init__.py
biondi/misc/infogan practice.py
biondi/misc/misc ai code.py
biondi/peters code for reference/__init__.py
biondi/peters code for reference/box delete.py
biondi/peters code for reference/client delete.py
biondi/peters code for reference/custom delete.py
biondi-0.1.6.1.dist-info/LICENSE
biondi-0.1.6.1.dist-info/METADATA
biondi-0.1.6.1.dist-info/WHEEL
biondi-0.1.6.1.dist-info/top_level.txt
biondi-0.1.6.1.dist-info/RECORD
