Metadata-Version: 2.1
Name: biondi
Version: 0.1.6.1
Summary: Machine learning code and resources for analyzing choroid plexus pathology
Home-page: https://github.com/mjneel/Biondi
Author: Michael Neel
Author-email: neelm@uci.edu
License: GNU GPLv3
Platform: UNKNOWN
Classifier: Programming Language :: Python :: 3
Requires-Python: >=3.8
License-File: LICENSE
